current_controller_sdk/__init__.py
current_controller_sdk/core.py
current_controller_api-1.0.0.dist-info/METADATA
current_controller_api-1.0.0.dist-info/WHEEL
current_controller_api-1.0.0.dist-info/top_level.txt
current_controller_api-1.0.0.dist-info/RECORD
