Metadata-Version: 2.1
Name: current-controller-api
Version: 1.0.0
Summary: 电流控制器串口通信SDK
Author: hxp
Author-email: rongaluo@163.com
Classifier: Programming Language :: Python :: 3
Classifier: License :: OSI Approved :: MIT License
Classifier: Operating System :: OS Independent
Requires-Python: >=3.6
